<?xml version="1.0" encoding="UTF-8"?>
<templates id="template" xml:space="preserve">
        <t t-name="pos_theme_sapphire.custom_header">
            		<div class="d-flex ms-2 me-2 mt-5 justify-content-between">
						<div class="d-flex gap-2">
								<div class="justify-content-center me-3 ms-3">
									<img 
											src="/pos_theme_sapphire/static/description/hi.png" 
											alt="Hi"/>

								</div>
								<div class="good_morning">
									<div class="d-flex gap-2">
										<span class="timer-day" t-esc="time.day"/> 
										<span class="timer-date" t-esc="time.date"/>
								    </div>
									<div class="d-flex gap-2 "> 
										<h3 >Good Morning <span t-esc="pos.user.name"/></h3>
										
									</div>
								</div>
						</div>
						 
                    <div class="timer-date-container d-flex flex-column smaller">
                        
                    </div>
						<div class="d-flex me-3 text-end ">
							<div class="timer-hours fs-1" t-esc="time.hours"> </div>
						</div>

					</div>
        </t>
</templates>
